karrio/mappers/sendle/__init__.py
karrio/mappers/sendle/mapper.py
karrio/mappers/sendle/proxy.py
karrio/mappers/sendle/settings.py
karrio/plugins/sendle/__init__.py
karrio/providers/sendle/__init__.py
karrio/providers/sendle/error.py
karrio/providers/sendle/rate.py
karrio/providers/sendle/tracking.py
karrio/providers/sendle/units.py
karrio/providers/sendle/utils.py
karrio/providers/sendle/shipment/__init__.py
karrio/providers/sendle/shipment/cancel.py
karrio/providers/sendle/shipment/create.py
karrio/schemas/sendle/__init__.py
karrio/schemas/sendle/cancel_request.py
karrio/schemas/sendle/cancel_response.py
karrio/schemas/sendle/error_responses.py
karrio/schemas/sendle/order_request.py
karrio/schemas/sendle/order_response.py
karrio/schemas/sendle/product_request.py
karrio/schemas/sendle/product_response.py
karrio/schemas/sendle/tracking_request.py
karrio/schemas/sendle/tracking_response.py
karrio_sendle-2026.1.4.dist-info/METADATA
karrio_sendle-2026.1.4.dist-info/WHEEL
karrio_sendle-2026.1.4.dist-info/entry_points.txt
karrio_sendle-2026.1.4.dist-info/top_level.txt
karrio_sendle-2026.1.4.dist-info/RECORD
